odoo/addons/search_engine_serializer_pydantic/README.rst
odoo/addons/search_engine_serializer_pydantic/__init__.py
odoo/addons/search_engine_serializer_pydantic/__manifest__.py
odoo/addons/search_engine_serializer_pydantic/i18n/it.po
odoo/addons/search_engine_serializer_pydantic/i18n/search_engine_serializer_pydantic.pot
odoo/addons/search_engine_serializer_pydantic/models/__init__.py
odoo/addons/search_engine_serializer_pydantic/models/se_index.py
odoo/addons/search_engine_serializer_pydantic/readme/CONTEXT.md
odoo/addons/search_engine_serializer_pydantic/readme/CONTRIBUTORS.md
odoo/addons/search_engine_serializer_pydantic/readme/CREDITS.md
odoo/addons/search_engine_serializer_pydantic/readme/DESCRIPTION.md
odoo/addons/search_engine_serializer_pydantic/readme/ROADMAP.md
odoo/addons/search_engine_serializer_pydantic/readme/USAGE.md
odoo/addons/search_engine_serializer_pydantic/static/description/icon.png
odoo/addons/search_engine_serializer_pydantic/static/description/index.html
odoo/addons/search_engine_serializer_pydantic/tools/__init__.py
odoo/addons/search_engine_serializer_pydantic/tools/serializer.py
odoo/addons/search_engine_serializer_pydantic/views/se_index.xml
odoo_addon_search_engine_serializer_pydantic-16.0.1.0.0.4.dist-info/METADATA
odoo_addon_search_engine_serializer_pydantic-16.0.1.0.0.4.dist-info/WHEEL
odoo_addon_search_engine_serializer_pydantic-16.0.1.0.0.4.dist-info/top_level.txt
odoo_addon_search_engine_serializer_pydantic-16.0.1.0.0.4.dist-info/RECORD
