Metadata-Version: 2.1
Name: odoo-addon-search-engine-serializer-pydantic
Version: 16.0.1.0.0.4
Summary: Defines base class for pydantic baser serializer
Home-page: https://github.com/OCA/search-engine
Author: ACSONE SA/NV,Odoo Community Association (OCA)
Author-email: support@odoo-community.org
License: AGPL-3
Platform: UNKNOWN
Classifier: Programming Language :: Python
Classifier: Framework :: Odoo
Classifier: Framework :: Odoo :: 16.0
Classifier: License :: OSI Approved :: GNU Affero General Public License v3
Requires-Python: >=3.10
Requires-Dist: odoo-addon-connector-search-engine <16.1dev,>=16.0dev
Requires-Dist: odoo-addon-pydantic <16.1dev,>=16.0dev
Requires-Dist: odoo <16.1dev,>=16.0a
Requires-Dist: pydantic
